{
  "parameters": [
    {
      "allowSymbolExpressionsInObject": false,
      "requiredOnCompile": false,
      "bindable": true,
      "propertySetterName": "setImg",
      "propertyGetterName": "getImg",
      "refTo": "",
      "name": "data-tchmi-img",
      "displayName": "img",
      "visible": true,
      "type": "tchmi:framework#/definitions/Path",
      "category": "",
      "description": "",
      "readOnly": false,
      "heritable": true,
      "propertyName": "img"
    }
  ],
  "virtualRights": [],
  "$schema": "./../../Packages/Beckhoff.TwinCAT.HMI.Framework.14.3.431/runtimes/native1.12-tchmi/Schema/UserControlConfig.Schema.json",
  "description": ""
}